gnss_collector/__init__.py
gnss_collector/socket_server.py
gnss_collector/engine/command_ui.py
gnss_collector/engine/engine.py
gnss_collector/engine/message.py
gnss_collector/engine/subscribe.py
gnss_collector/engine/conf/settings.py
gnss_collector/engine/conf/settings.tpl.py
gnss_collector/engine/ventanas_modales/station/__init__.py
gnss_collector/engine/ventanas_modales/station/borrar.py
gnss_collector/engine/ventanas_modales/station/crear.py
gnss_collector/engine/ventanas_modales/station/guardar.py
gnss_collector/local/__init__.py
gnss_collector/local/adjustments.py
gnss_collector/local/adjustments.tpl.py
gnss_collector/local/run.py
gnss_collector/local/test_server_socket.py
gnss_collector/network/remote.py
gnss_collector/network/remote_manager.py
gnss_collector/scripts/__init__.py
gnss_collector/scripts/adjustments.py
gnss_collector/scripts/collector_example.json
gnss_collector/scripts/run_collector.py
gnss_collector/scripts/.mypy_cache/3.8/@plugins_snapshot.json
gnss_collector/scripts/.mypy_cache/3.8/_ast.data.json
gnss_collector/scripts/.mypy_cache/3.8/_ast.meta.json
gnss_collector/scripts/.mypy_cache/3.8/_importlib_modulespec.data.json
gnss_collector/scripts/.mypy_cache/3.8/_importlib_modulespec.meta.json
gnss_collector/scripts/.mypy_cache/3.8/_thread.data.json
gnss_collector/scripts/.mypy_cache/3.8/_thread.meta.json
gnss_collector/scripts/.mypy_cache/3.8/_types.data.json
gnss_collector/scripts/.mypy_cache/3.8/_types.meta.json
gnss_collector/scripts/.mypy_cache/3.8/abc.data.json
gnss_collector/scripts/.mypy_cache/3.8/abc.meta.json
gnss_collector/scripts/.mypy_cache/3.8/array.data.json
gnss_collector/scripts/.mypy_cache/3.8/array.meta.json
gnss_collector/scripts/.mypy_cache/3.8/ast.data.json
gnss_collector/scripts/.mypy_cache/3.8/ast.meta.json
gnss_collector/scripts/.mypy_cache/3.8/builtins.data.json
gnss_collector/scripts/.mypy_cache/3.8/builtins.meta.json
gnss_collector/scripts/.mypy_cache/3.8/codecs.data.json
gnss_collector-2.0.4.dist-info/METADATA
gnss_collector-2.0.4.dist-info/WHEEL
gnss_collector-2.0.4.dist-info/entry_points.txt
gnss_collector-2.0.4.dist-info/top_level.txt
gnss_collector-2.0.4.dist-info/RECORD
